masquerade/__init__.py
masquerade/assign_new_values.py
masquerade/configure_claude.py
masquerade/get_pdf_text.py
masquerade/get_sensitive_data.py
masquerade/mcp_pdf_redaction.py
masquerade/redact_per_pdf.py
masquerade/remove_values.py
masquerade/replace_text_pdf_fitz.py
masquerade/replace_text_pdf_spire.py
masquerade/tinfoil_llm.py
mseep_masquerade-0.2.1.dist-info/METADATA
mseep_masquerade-0.2.1.dist-info/WHEEL
mseep_masquerade-0.2.1.dist-info/licenses/LICENSE
mseep_masquerade-0.2.1.dist-info/licenses/LICENSED-MATERIALS.txt
mseep_masquerade-0.2.1.dist-info/RECORD
