Metadata-Version: 2.4
Name: mseep-masquerade
Version: 0.2.1
Summary: A privacy firewall for PDF files that automatically detects and redacts sensitive data
Author-email: mseep <support@skydeck.ai>
License-File: LICENSE
License-File: LICENSED-MATERIALS.txt
Requires-Python: <3.13,>=3.10.0
Requires-Dist: fastmcp==0.4.1
Requires-Dist: mcp==1.3.0
Requires-Dist: pymupdf==1.23.8
Requires-Dist: tinfoil
